keygim/__init__.py
keygim/imageUtils.py
keygim/keygim.py
keygim-1.0.0.dist-info/LICENSE
keygim-1.0.0.dist-info/METADATA
keygim-1.0.0.dist-info/WHEEL
keygim-1.0.0.dist-info/top_level.txt
keygim-1.0.0.dist-info/RECORD
