Metadata-Version: 2.1
Name: keygim
Version: 1.0.0
Summary: A library used to download images from Google.
Home-page: https://github.com/keyywind/keygim
Author: Keywind
Author-email: kevinwater127@gmail.com
Project-URL: Bug Tracker, https://github.com/keyywind/keygim/issues
Classifier: Programming Language :: Python :: 3
Classifier: License :: OSI Approved :: MIT License
Classifier: Operating System :: OS Independent
Requires-Python: >=3.6
License-File: LICENSE
Requires-Dist: markdown
Requires-Dist: scikit-image
Requires-Dist: PyAutoGUI
Requires-Dist: pynput
Requires-Dist: numpy
Requires-Dist: opencv-python
Requires-Dist: keyscraper
